oscar_pg_search/__init__.py
oscar_pg_search/apps.py
oscar_pg_search/forms.py
oscar_pg_search/mixins.py
oscar_pg_search/order_by_options.py
oscar_pg_search/postgres_search_handler.py
oscar_pg_search/utils.py
oscar_pg_search/filter_options/__init__.py
oscar_pg_search/filter_options/attribute_fields.py
oscar_pg_search/filter_options/base_fields.py
oscar_pg_search/filter_options/base_form.py
oscar_pg_search/filter_options/filter_forms.py
oscar_pg_search/filter_options/offer_fields.py
oscar_pg_search/filter_options/product_fields.py
oscar_pg_search/templates/oscar_pg_search/catalogue/partials/filter_forms.html
oscar_pg_search/templates/oscar_pg_search/partials/search.html
oscar_pg_search/templatetags/__init__.py
oscar_pg_search/templatetags/oscar_pg_search.py
django_oscar_pg_search-0.9.10.dist-info/LICENSE
django_oscar_pg_search-0.9.10.dist-info/METADATA
django_oscar_pg_search-0.9.10.dist-info/WHEEL
django_oscar_pg_search-0.9.10.dist-info/top_level.txt
django_oscar_pg_search-0.9.10.dist-info/RECORD
