Metadata-Version: 2.1
Name: django-oscar-pg-search
Version: 0.9.10
Summary: Pure Postgresql search backend for Django Oscar
Author: Snake-Soft
Author-email: info@snake-soft.com
License: BSD
Classifier: Development Status :: 4 - Beta
Classifier: Environment :: Web Environment
Classifier: Framework :: Django
Classifier: Framework :: Django :: 3.0
Classifier: Framework :: Django :: 3.1
Classifier: Framework :: Django :: 3.2
Classifier: Intended Audience :: Developers
Classifier: License :: OSI Approved :: BSD License
Classifier: Operating System :: Unix
Classifier: Programming Language :: Python
Classifier: Programming Language :: Python :: 3
Classifier: Programming Language :: Python :: 3.7
Classifier: Programming Language :: Python :: 3.8
Classifier: Programming Language :: Python :: 3.9
License-File: LICENSE
Requires-Dist: django <5,>=3.0
Requires-Dist: django-oscar <3.3,>=2.0
Provides-Extra: test
Requires-Dist: coverage <5.6,>=5.5 ; extra == 'test'
